{
  "name": "managing-intelligence-lifecycle",
  "description": "Manages the end-to-end cyber threat intelligence lifecycle from planning and direction through collection, processing, analysis, dissemination, and feedback to ensure intelligence products meet stakeholder requirements and continuously improve. Use when establishing or maturing a CTI program, defining intelligence requirements with business stakeholders, or building feedback loops between intelligence consumers and producers. Activates for requests involving CTI program maturity, intelligence requirements, PIRs, or intelligence lifecycle management.",
  "imported_at": "2026-06-18T01:21:19Z",
  "metadata": {
    "domain": "cybersecurity",
    "subdomain": "threat-intelligence",
    "tags": [
      "CTI",
      "intelligence-lifecycle",
      "PIR",
      "NIST-SP-800-150",
      "threat-intelligence-program",
      "NIST-CSF"
    ],
    "version": "1.0.0",
    "author": "team-cybersecurity",
    "license": "Apache-2.0",
    "nist_csf": [
      "ID.RA-01",
      "ID.RA-05",
      "DE.CM-01",
      "DE.AE-02"
    ],
    "mitre_attack": [
      "T1591",
      "T1592",
      "T1593",
      "T1589"
    ]
  },
  "resources": [
    "scripts/agent.py",
    "references/api-reference.md"
  ]
}