{
  "name": "competition-jwt-claim-confusion",
  "description": "Internal downstream skill for ctf-sandbox-orchestrator. CTF-sandbox workflow for JWT, JWS, and JWE validation paths, header parsing, key selection, claim acceptance, audience and issuer checks, role derivation, and token-to-identity confusion bugs. Use when the user asks to inspect JWT headers or claims, key lookup, `kid` handling, `alg` confusion, audience or issuer validation, role claims, or explain how a token becomes accepted identity or privilege. Use only after `$ctf-sandbox-orchestrator` has already established sandbox assumptions and routed here.",
  "imported_at": "2026-06-21T06:03:24Z",
  "metadata": {},
  "resources": [
    "references/jwt-claim-confusion.md"
  ]
}