{
  "name": "performing-memory-forensics-with-volatility3",
  "description": "Analyze volatile memory dumps using Volatility 3 to extract running processes, network connections, loaded modules, and evidence of malicious activity.",
  "imported_at": "2026-06-18T01:21:19Z",
  "metadata": {
    "domain": "cybersecurity",
    "subdomain": "digital-forensics",
    "tags": [
      "forensics",
      "memory-forensics",
      "volatility",
      "ram-analysis",
      "malware-detection",
      "incident-response"
    ],
    "version": "1.0",
    "author": "mahipal",
    "license": "Apache-2.0",
    "nist_csf": [
      "RS.AN-01",
      "RS.AN-03",
      "DE.AE-02",
      "RS.MA-01"
    ],
    "mitre_attack": [
      "T1005",
      "T1074",
      "T1119",
      "T1070",
      "T1059"
    ]
  },
  "resources": [
    "scripts/agent.py",
    "references/api-reference.md"
  ]
}